pyctrld/__init__.py
pyctrld/_api.py
pyctrld/_core/__init__.py
pyctrld/_core/exceptions.py
pyctrld/_core/logger.py
pyctrld/_core/urls.py
pyctrld/_core/utils.py
pyctrld/_core/models/__init__.py
pyctrld/_core/models/access.py
pyctrld/_core/models/account.py
pyctrld/_core/models/analytics.py
pyctrld/_core/models/billing.py
pyctrld/_core/models/common.py
pyctrld/_core/models/devices.py
pyctrld/_core/models/misc.py
pyctrld/_core/models/organization.py
pyctrld/_core/models/services.py
pyctrld/_core/models/profiles/__init__.py
pyctrld/_core/models/profiles/custom_rules.py
pyctrld/_core/models/profiles/filters.py
pyctrld/_core/models/profiles/list_proxies.py
pyctrld/_core/models/profiles/profiles.py
pyctrld/_core/models/profiles/rule_folders.py
pyctrld/_core/models/profiles/services.py
pyctrld/api/__init__.py
pyctrld/api/access.py
pyctrld/api/account.py
pyctrld/api/analytics.py
pyctrld/api/billing.py
pyctrld/api/devices.py
pyctrld/api/misc.py
pyctrld/api/mobile_config.py
pyctrld/api/organization.py
pyctrld/api/services.py
pyctrld/api/profiles/__init__.py
pyctrld/api/profiles/_api.py
pyctrld/api/profiles/custom_rules.py
pyctrld/api/profiles/default_rule.py
pyctrld/api/profiles/filters.py
pyctrld/api/profiles/list_proxies.py
pyctrld/api/profiles/profiles.py
pyctrld/api/profiles/rule_folders.py
pyctrld/api/profiles/services.py
pyctrld-0.1.3.dist-info/licenses/LICENSE
pyctrld-0.1.3.dist-info/METADATA
pyctrld-0.1.3.dist-info/WHEEL
pyctrld-0.1.3.dist-info/top_level.txt
pyctrld-0.1.3.dist-info/RECORD
