Metadata-Version: 2.4
Name: pyctrld
Version: 0.1.3
Summary: Non-official Control D API for Python
Author-email: xenolex <alexey.belkov@gmail.com>
License: MIT
Project-URL: Homepage, https://github.com/xenolex/PyCtrlD
Project-URL: Documentation, https://github.com/xenolex/PyCtrlD#readme
Project-URL: Repository, https://github.com/xenolex/PyCtrlD
Project-URL: Bug Tracker, https://github.com/xenolex/PyCtrlD/issues
Keywords: controld,dns,api,client,privacy,ad-blocking
Classifier: Development Status :: 4 - Beta
Classifier: Intended Audience :: Developers
Classifier: License :: OSI Approved :: MIT License
Classifier: Programming Language :: Python :: 3
Classifier: Programming Language :: Python :: 3.10
Classifier: Programming Language :: Python :: 3.11
Classifier: Programming Language :: Python :: 3.12
Classifier: Programming Language :: Python :: 3.13
Classifier: Topic :: Internet :: Name Service (DNS)
Classifier: Topic :: Software Development :: Libraries :: Python Modules
Requires-Python: >=3.10
License-File: LICENSE
Requires-Dist: pydantic>=2.11.9
Requires-Dist: requests>=2.32.5
Requires-Dist: backports.strenum>=1.0.0; python_version < "3.11"
Dynamic: license-file
